c3linear/__init__.py
c3linear/mro.py
tests/__init__.py
tests/conftest.py
tests/test_mro.py
c3linear-0.1.1.dist-info/LICENSE
c3linear-0.1.1.dist-info/METADATA
c3linear-0.1.1.dist-info/WHEEL
c3linear-0.1.1.dist-info/top_level.txt
c3linear-0.1.1.dist-info/RECORD
