Metadata-Version: 2.1
Name: c3linear
Version: 0.1.1
Summary: A naive implementation of C3 linearization algorithm used in Python's MRO
Home-page: https://github.com/pilosus/c3linear
Author: Vitaly R. Samigullin
Author-email: vrs@pilosus.org
License: UNKNOWN
Download-URL: https://github.com/pilosus/c3linear/archive/0.1.1.tar.gz
Platform: UNKNOWN
Classifier: Development Status :: 3 - Alpha
Classifier: Environment :: Console
Classifier: Intended Audience :: Education
Classifier: Programming Language :: Python :: 3
Classifier: License :: OSI Approved :: MIT License
Classifier: Topic :: Education
Classifier: Typing :: Typed
Requires-Python: >=3.6
Provides-Extra: extra
Requires-Dist: mypy ; extra == 'extra'
